flask_jwt_consumer/__init__.py
flask_jwt_consumer/config.py
flask_jwt_consumer/decorators.py
flask_jwt_consumer/errors.py
flask_jwt_consumer/flask_jwt_consumer.py
flask_jwt_consumer/helpers.py
flask_jwt_consumer-1.1.0.dist-info/LICENSE
flask_jwt_consumer-1.1.0.dist-info/METADATA
flask_jwt_consumer-1.1.0.dist-info/WHEEL
flask_jwt_consumer-1.1.0.dist-info/top_level.txt
flask_jwt_consumer-1.1.0.dist-info/RECORD
