Metadata-Version: 2.1
Name: flask-jwt-consumer
Version: 1.1.0
Summary: Flask JWT consumer with multi public key support
Home-page: https://github.com/dmi3y/flask-jwt-consumer
Author: Dmitrii Lapshukov
Author-email: lapshukov@gmail.com
License: UNKNOWN
Keywords: jwt,jwt-consumer,jwt-validation,authentication,autherization,multi-issuer
Platform: UNKNOWN
Classifier: Programming Language :: Python :: 3
Classifier: License :: OSI Approved :: MIT License
Classifier: Operating System :: OS Independent
Requires-Dist: Flask
Requires-Dist: PyJWT
Requires-Dist: cryptography
